gaek/__init__.py
gaek/environ.py
gaek/ndb_json.py
gaek-0.4.1.dist-info/LICENSE
gaek-0.4.1.dist-info/METADATA
gaek-0.4.1.dist-info/WHEEL
gaek-0.4.1.dist-info/top_level.txt
gaek-0.4.1.dist-info/RECORD
