Metadata-Version: 2.1
Name: gaek
Version: 0.4.1
Summary: A collection of useful tools for Python apps running on Google App Engine.
Home-page: https://github.com/erichiggins/gaek
Author: Eric Higgins
Author-email: erichiggins@gmail.com
License: BSD
Platform: UNKNOWN
Requires-Dist: python-dateutil (>=2.4.2)
